ironGatingDesign/__init__.py
ironGatingDesign/gatingDesign.py
irongatingdesign-0.2.0.dist-info/METADATA
irongatingdesign-0.2.0.dist-info/WHEEL
irongatingdesign-0.2.0.dist-info/RECORD
