Metadata-Version: 2.1
Name: irongatingdesign
Version: 0.2.0
Summary: gating design for iron casting
License: MIT
Author: Anan Khongchuai
Requires-Python: >=3.8,<4.0
Classifier: License :: OSI Approved :: MIT License
Classifier: Programming Language :: Python :: 3
Classifier: Programming Language :: Python :: 3.8
Classifier: Programming Language :: Python :: 3.9
Classifier: Programming Language :: Python :: 3.10
Classifier: Programming Language :: Python :: 3.11
